hyperiontf/__init__.py
hyperiontf/api/__init__.py
hyperiontf/api/rest_client/__init__.py
hyperiontf/api/rest_client/client.py
hyperiontf/api/rest_client/request.py
hyperiontf/api/rest_client/response.py
hyperiontf/assertions/__init__.py
hyperiontf/assertions/decorators.py
hyperiontf/assertions/expect.py
hyperiontf/assertions/expectation_result.py
hyperiontf/assertions/helpers.py
hyperiontf/assertions/image_expectation_result.py
hyperiontf/assertions/strategy/__init__.py
hyperiontf/assertions/strategy/array_strategy.py
hyperiontf/assertions/strategy/color_strategy.py
hyperiontf/assertions/strategy/decorators.py
hyperiontf/assertions/strategy/default_strategy.py
hyperiontf/assertions/strategy/dict_strategy.py
hyperiontf/assertions/strategy/filesystem_strategy.py
hyperiontf/assertions/strategy/image_strategy.py
hyperiontf/assertions/strategy/numeric_strategy.py
hyperiontf/assertions/strategy/string_strategy.py
hyperiontf/cli/__init__.py
hyperiontf/cli/base_shell.py
hyperiontf/cli/cli_client.py
hyperiontf/cli/helperes/__init__.py
hyperiontf/cli/helperes/ansi_escape.py
hyperiontf/cli/ssh_client.py
hyperiontf/configuration/__init__.py
hyperiontf/configuration/capabilities.py
hyperiontf/configuration/config.py
hyperiontf/configuration/section.py
hyperiontf/configuration/sections/__init__.py
hyperiontf/configuration/sections/cli.py
hyperiontf/configuration/sections/desktop_capabilities.py
hyperiontf/configuration/sections/element.py
hyperiontf/configuration/sections/logger.py
hyperiontf/configuration/sections/mobile_capabilities.py
hyperiontf/configuration/sections/page_object.py
hyperiontf/configuration/sections/rest.py
hyperiontf/configuration/sections/visual.py
hyperiontf/configuration/sections/web_capabilities.py
hyperiontf/exception.py
hyperiontf/executors/__init__.py
hyperiontf/executors/pytest/__init__.py
hyperiontf/executors/pytest/fixture.py
hyperiontf/executors/pytest/helper/test_case.py
hyperiontf/executors/pytest/setup.py
hyperiontf/fs/__init__.py
hyperiontf-0.6.21.dist-info/LICENSE
hyperiontf-0.6.21.dist-info/METADATA
hyperiontf-0.6.21.dist-info/WHEEL
hyperiontf-0.6.21.dist-info/RECORD
