Metadata-Version: 2.1
Name: hyperiontf
Version: 0.6.21
Summary: Hyperion Testing Framework
License: Apache 2.0 License
Author: Oleksiy Bondar
Author-email: bondaroleksiyandriyovich@gmail.com
Requires-Python: >=3.11,<4.0
Classifier: License :: Other/Proprietary License
Classifier: Programming Language :: Python :: 3
Classifier: Programming Language :: Python :: 3.11
Requires-Dist: Appium-Python-Client (>=3.2.0,<4.0.0)
Requires-Dist: jsonschema (>=4.23.0,<5.0.0)
Requires-Dist: lxml (>=5.3.0,<6.0.0)
Requires-Dist: opencv-contrib-python (>=4.9.0.80,<5.0.0.0)
Requires-Dist: opencv-python (>=4.9.0.80,<5.0.0.0)
Requires-Dist: opencv-python-headless (>=4.9.0.80,<5.0.0.0)
Requires-Dist: paramiko (>=3.5.0,<4.0.0)
Requires-Dist: playwright (>=1.46.0,<2.0.0)
Requires-Dist: ply (>=3.11,<4.0)
Requires-Dist: ptyprocess (>=0.7.0,<0.8.0)
Requires-Dist: requests (>=2.31.0,<3.0.0)
Requires-Dist: selenium (>=4.24.0,<5.0.0)
Requires-Dist: webdriver_manager (>=4.0.2,<5.0.0)
